setup.py
dome/__init__.py
dome/dome.py
dome/utils.py
dome.egg-info/PKG-INFO
dome.egg-info/SOURCES.txt
dome.egg-info/dependency_links.txt
dome.egg-info/entry_points.txt
dome.egg-info/top_level.txt
test/test_body.py
test/test_div.py
test/test_head.py
test/test_html.py
test/test_meta.py