Metadata-Version: 1.0
Name: dome
Version: 0.0.1
Summary: Python DOM Element template
Home-page: https://github.com/qorzj/dome
Author: qorzj
Author-email: inull@qq.com
License: MIT
Keywords: dome dom lessweb
Platform: any
